feishuer/__init__.py
feishuer/__version__.py
feishuer/bot.py
feishuer/errors.py
feishuer/log.py
feishuer-0.2.3.dist-info/LICENSE
feishuer-0.2.3.dist-info/METADATA
feishuer-0.2.3.dist-info/WHEEL
feishuer-0.2.3.dist-info/top_level.txt
feishuer-0.2.3.dist-info/RECORD
